dictionary/__init__.py
dictionary/dictionary.py
Radman1.0.0_dictionary-2.0.0.dist-info/METADATA
Radman1.0.0_dictionary-2.0.0.dist-info/WHEEL
Radman1.0.0_dictionary-2.0.0.dist-info/top_level.txt
Radman1.0.0_dictionary-2.0.0.dist-info/RECORD
