Metadata-Version: 2.1
Name: Radman1.0.0-dictionary
Version: 2.0.0
Summary: UNKNOWN
Author: Radman Lotfiazar
License: UNKNOWN
Platform: UNKNOWN
Requires-Python: >=3.8
Requires-Dist: requests (>=2.23.0)
